LICENSE
MANIFEST.in
readme.md
setup.py
bp_storage/__init__.py
bp_storage/beard.py
bp_storage/classification.py
bp_storage/kitti.py
bp_storage.egg-info/PKG-INFO
bp_storage.egg-info/SOURCES.txt
bp_storage.egg-info/dependency_links.txt
bp_storage.egg-info/not-zip-safe
bp_storage.egg-info/requires.txt
bp_storage.egg-info/top_level.txt
bp_storage/utils/__init__.py
bp_storage/utils/common.py
bp_storage/utils/const.py
bp_storage/utils/datasets.py
bp_storage/utils/images.py