Metadata-Version: 2.1
Name: bp-storage
Version: 1.0.1
Summary: Helper Library for various Dataset formats
Home-page: https://github.com/BrainPlugAI/bp-storage
Author: Felix Geilert
Author-email: f.geilert@brainplug.de
License: MIT License
Keywords: storage datasets deep learning
Platform: UNKNOWN
Classifier: Programming Language :: Python :: 3.5
Classifier: Topic :: Scientific/Engineering :: Artificial Intelligence
